ingredient_parser/__init__.py
ingredient_parser/_common.py
ingredient_parser/dataclasses.py
ingredient_parser/parsers.py
ingredient_parser/pint_extensions.txt
ingredient_parser/py.typed
ingredient_parser/en/__init__.py
ingredient_parser/en/_constants.py
ingredient_parser/en/_embeddings.py
ingredient_parser/en/_loaders.py
ingredient_parser/en/_regex.py
ingredient_parser/en/_structure_features.py
ingredient_parser/en/_utils.py
ingredient_parser/en/parser.py
ingredient_parser/en/postprocess.py
ingredient_parser/en/preprocess.py
ingredient_parser/en/data/ModelCard.en.md
ingredient_parser/en/data/fdc_ingredients.csv.gz
ingredient_parser/en/data/ingredient_embeddings.35d.glove.txt.gz
ingredient_parser/en/data/ingredient_tagdict.json.gz
ingredient_parser/en/data/model.en.crfsuite
ingredient_parser/en/foundationfoods/__init__.py
ingredient_parser/en/foundationfoods/_bm25.py
ingredient_parser/en/foundationfoods/_ff_constants.py
ingredient_parser/en/foundationfoods/_ff_dataclasses.py
ingredient_parser/en/foundationfoods/_ff_utils.py
ingredient_parser/en/foundationfoods/_foundationfoods.py
ingredient_parser/en/foundationfoods/_fuzzy.py
ingredient_parser/en/foundationfoods/_usif.py
ingredient_parser_nlp-2.5.0.dist-info/licenses/LICENSE
ingredient_parser_nlp-2.5.0.dist-info/METADATA
ingredient_parser_nlp-2.5.0.dist-info/WHEEL
ingredient_parser_nlp-2.5.0.dist-info/top_level.txt
ingredient_parser_nlp-2.5.0.dist-info/RECORD
