Metadata-Version: 2.4
Name: ingredient_parser_nlp
Version: 2.5.0
Summary: A Python package to parse structured information from recipe ingredient sentences
Author-email: Tom Strange <tpstrange@gmail.com>
License-Expression: MIT
Project-URL: Homepage, https://github.com/strangetom/ingredient-parser/
Project-URL: Documentation, https://ingredient-parser.readthedocs.io/en/latest/
Project-URL: Source, https://github.com/strangetom/ingredient-parser
Project-URL: Changelog, https://github.com/strangetom/ingredient-parser/blob/master/CHANGELOG.md
Keywords: recipe,ingredient,ingredients,nlp,parsing
Classifier: Development Status :: 5 - Production/Stable
Classifier: Natural Language :: English
Classifier: Operating System :: OS Independent
Classifier: Programming Language :: Python :: 3 :: Only
Classifier: Programming Language :: Python :: 3.11
Classifier: Programming Language :: Python :: 3.12
Classifier: Programming Language :: Python :: 3.13
Classifier: Programming Language :: Python :: 3.14
Classifier: Topic :: Text Processing :: Linguistic
Requires-Python: >=3.11
License-File: LICENSE
Requires-Dist: nltk>=3.9.1
Requires-Dist: python-crfsuite
Requires-Dist: pint>=0.25.0
Requires-Dist: numpy
Dynamic: license-file
